[
  {
    "id": 1772719403373,
    "username": "A@1",
    "password": "$2b$10$QLsW9X8JKXB5tnDp4277lOU.Qav5l2X9xxnYWQDaEOXTtqjjPNigS"
  },
  {
    "id": 1772719443187,
    "username": "aditya0820.becse24@chitkara.edu.in",
    "password": "$2b$10$wGiCB378/f1zXqxTXdiMquvEkiJ.7MGLWBNJnTZ4vh0D8uLRqfZDO",
    "budget": 1000
  },
  {
    "id": 1772724774132,
    "username": "af@12",
    "password": "$2b$10$mgoVzErF2tmWPtvkYBf1COH8L1Jt41OjFqqTiOjEZwr4Mow594Oc6"
  },
  {
    "id": 1772725240581,
    "username": "Ad@123",
    "password": "$2b$10$NCoA.YELwd27JR3qnTCwF.X14uD3vXlZJwfZlB92cY0OWAHB3K/L2"
  },
  {
    "id": 1772725284297,
    "username": "As@2",
    "password": "$2b$10$ISdP7sKED13C5CdrRxh96OJ0zZJgw9FyZN3cWPa6/ZU4/1zojoKP6"
  },
  {
    "id": 1772725420878,
    "username": "sa@1",
    "password": "$2b$10$PpfjUEwV6Ezo24P9lnqEBOBa0riWgWxOT1PH23HtVV3lX/O9dFIgC"
  },
  {
    "id": 1772725658217,
    "username": "sa@2",
    "password": "$2b$10$x.jrP1O.rpB/3fQlYRGUZepTMasmHZlmJ4CmWKMVjJhJVjLmErujq"
  },
  {
    "id": 1772811150291,
    "username": "aditya0820.becse24@chitkara.edu.in",
    "password": "$2b$10$rzwp07oKJyCXDSd3Poh3wu3heTJpXFtLAtf//ficI8fp.WVpO6QL."
  },
  {
    "id": 1773060604615,
    "username": "abhey0814.becse24@chitkara.edu.in",
    "password": "$2b$10$fZVj/oKCbQJFnaDU5Fz4ZOCLQdwh06nYmG2qBYMDVCQjZni9zLvcW",
    "budget": 10000
  },
  {
    "id": 1773124084277,
    "username": "aditya0820.becse24@chitkara.edu.in",
    "password": "$2b$10$AyUAqBptbAtvCs34QScxVOC0Sb0eCjLYw/kp3RU4Jlrx.El6NGiFi",
    "budget": null
  },
  {
    "id": 1773226954549,
    "username": "Adi@1",
    "password": "$2b$10$pvrCUUsbqCXThzXSh.Q5yeEN31/fZwUD3lx72UL3r8FwaHnwSmuEy",
    "budget": 100
  },
  {
    "id": 1776776015837,
    "username": "Abc",
    "password": "$2b$10$LTX/LLLladUZzKKrZc96xO1TkKi6LLxTR8KqQKpFFsYamRO.6BpRW",
    "budget": null
  },
  {
    "id": 1776776052043,
    "username": "abc",
    "password": "$2b$10$57JLJWQG7jDsg7Oq.mBFC.KfmFfLbnObIBjnqvfJ2L12eRgjq2T.C",
    "budget": null
  },
  {
    "id": 1776776425012,
    "username": "a",
    "password": "$2b$10$N/Z2cMIU8O1aVXs6VGu9Y.EuyPPZlNw.YDia2S4XHXXhcEaGKcKeG",
    "budget": null
  }
]